kscorer/__init__.py
kscorer/kscorer.py
kscorer/pmixin.py
kscorer-2.2.0.dist-info/LICENSE
kscorer-2.2.0.dist-info/METADATA
kscorer-2.2.0.dist-info/WHEEL
kscorer-2.2.0.dist-info/top_level.txt
kscorer-2.2.0.dist-info/RECORD
