Metadata-Version: 2.1
Name: kscorer
Version: 2.2.0
Summary: Auto-select optimal K-means clusters with advanced scoring
Author-email: Volodymyr Holomb <wldmrgml@gmail.com>
License: GNU GENERAL PUBLIC LICENSE
Project-URL: Source, https://github.com/woldemarg/kscorer
Project-URL: Home, https://github.com/woldemarg/kscorer
Project-URL: Author, https://www.linkedin.com/in/vholomb
Keywords: visualization,analysis,clustering
Classifier: Development Status :: 4 - Beta
Classifier: License :: OSI Approved :: GNU General Public License v3 (GPLv3)
Classifier: Programming Language :: Python
Classifier: Topic :: Scientific/Engineering
Requires-Python: >=3.9
License-File: LICENSE
Requires-Dist: kneefinder >=0.0.2
Requires-Dist: pandas >=1.5.3
Requires-Dist: scikit-learn >=1.2.2
Requires-Dist: seaborn >=0.12
Requires-Dist: tqdm >=4.66.1
